Metadata-Version: 1.1
Name: bashplotlib
Version: 0.6.5
Summary: plotting in the terminal
Home-page: https://github.com/glamp/bashplotlib
Author: Greg Lamp
Author-email: lamp.greg@gmail.com
License: BSD
Keywords: plotting,console,shell
Platform: UNKNOWN
Classifier: Environment :: Console
Classifier: Intended Audience :: End Users/Desktop
Classifier: License :: OSI Approved :: BSD License
Classifier: Programming Language :: Python :: 2.7
Classifier: Programming Language :: Python :: 3
